hermai/core/explainer.py
hermai/core/explanation.py
hermai/explainers/__init__.py
hermai/explainers/base.py
hermai/explainers/general.py
hermai/explainers/local.py
hermai/perturbations/__init__.py
hermai/perturbations/base_generator.py
hermai/perturbations/tabular.py
hermai/perturbations/tabular_generator.py
hermai/visualizations/plots.py
hermai-0.1.8.dist-info/licenses/LICENSE
hermai-0.1.8.dist-info/METADATA
hermai-0.1.8.dist-info/WHEEL
hermai-0.1.8.dist-info/top_level.txt
hermai-0.1.8.dist-info/RECORD
